phenome_utils/__init__.py
phenome_utils/main.py
phenome_utils/phenome_utils.py
phenome_utils-0.7.0.dist-info/LICENSE
phenome_utils-0.7.0.dist-info/METADATA
phenome_utils-0.7.0.dist-info/WHEEL
phenome_utils-0.7.0.dist-info/top_level.txt
phenome_utils-0.7.0.dist-info/RECORD
