Metadata-Version: 2.1
Name: phenome_utils
Version: 0.7.0
Summary: A Python package for data manipulation and analysis utilities
Home-page: https://git.phenome.health/trent.leslie/phenome-utils
Author: Trent Leslie
Author-email: trent.leslie@phenomehealth.org
License: MIT
Keywords: data analysis pandas utilities arivale snapshots
Classifier: Development Status :: 3 - Alpha
Classifier: Intended Audience :: Developers
Classifier: License :: OSI Approved :: MIT License
Classifier: Programming Language :: Python :: 3
Classifier: Programming Language :: Python :: 3.8
Classifier: Programming Language :: Python :: 3.9
Classifier: Programming Language :: Python :: 3.10
Classifier: Programming Language :: Python :: 3.11
Requires-Python: >=3.8
License-File: LICENSE
Requires-Dist: pandas
Requires-Dist: numpy
Requires-Dist: matplotlib
Provides-Extra: dev
Requires-Dist: pytest ; extra == 'dev'
Requires-Dist: pytest-cov ; extra == 'dev'
Requires-Dist: flake8 ; extra == 'dev'
